tensorflow3d_transforms/__init__.py
tensorflow3d_transforms/rotation_conversions.py
tensorflow3d_transforms/so3_ops.py
tensorflow3d_transforms/version.py
tensorflow3dtransforms-0.1.0.dist-info/LICENSE
tensorflow3dtransforms-0.1.0.dist-info/METADATA
tensorflow3dtransforms-0.1.0.dist-info/WHEEL
tensorflow3dtransforms-0.1.0.dist-info/top_level.txt
tensorflow3dtransforms-0.1.0.dist-info/RECORD
